{
    "type":"Live2D Model Setting",
    "name":"mysubaru",
    "model":"moc/mysubaru.moc",
    "textures":[
        "moc/mysubaru.1024/texture_00.png"],
    "physics":"mysubaru.physics.json",
    "pose":"mysubaru.pose.json",
    "layout":{
        "center_x":0,
        "y":1.2,
        "width":2.4
    },
    "hit_areas":[
        {
            "name":"head",
            "id":"D_REF.PT_FACE,D_FACE.04,D_FACE.01,D_REF.PT_HAIR_FRONT,D_HAIR_FRONT.01,D_HAIR_BACK.03,D_HAIR_BACK.04,D_HAIR_BACK.01"
        },
        {
            "name":"body",
            "id":"D_REF.PT_BODY_STOMACH,D_REF.PT_BODY_CHEST"
        }],
    "motions":{
        "idle":[
            {
                "file":"mtn/idle_00.mtn",
                "fade_in":2000,
                "fade_out":2000
            },
            {
                "file":"mtn/idle_01.mtn",
                "fade_in":2000,
                "fade_out":2000
            },
            {
                "file":"mtn/idle_02.mtn",
                "fade_in":2000,
                "fade_out":2000
            }],
        "tap_body":[
            {
                "file":"mtn/tapBody_00.mtn",
                "sound":"snd/tapBody_00.mp3"
            },
            {
                "file":"mtn/tapBody_01.mtn",
                "sound":"snd/tapBody_01.mp3"
            },
            {
                "file":"mtn/tapBody_02.mtn",
                "sound":"snd/tapBody_02.mp3"
            }],
        "pinch_in":[
            {
                "file":"mtn/pinchIn_00.mtn",
                "sound":"snd/pinchIn_00.mp3"
            },
            {
                "file":"mtn/pinchIn_01.mtn",
                "sound":"snd/pinchIn_01.mp3"
            },
            {
                "file":"mtn/pinchIn_02.mtn",
                "sound":"snd/pinchIn_02.mp3"
            }],
        "pinch_out":[
            {
                "file":"mtn/pinchOut_00.mtn",
                "sound":"snd/pinchOut_00.mp3"
            },
            {
                "file":"mtn/pinchOut_01.mtn",
                "sound":"snd/pinchOut_01.mp3"
            },
            {
                "file":"mtn/pinchOut_02.mtn",
                "sound":"snd/pinchOut_02.mp3"
            }],
        "shake":[
            {
                "file":"mtn/shake_00.mtn",
                "sound":"snd/shake_00.mp3",
                "fade_in":500
            },
            {
                "file":"mtn/shake_01.mtn",
                "sound":"snd/shake_01.mp3",
                "fade_in":500
            },
            {
                "file":"mtn/shake_02.mtn",
                "sound":"snd/shake_02.mp3",
                "fade_in":500
            }],
        "flick_head":[
            {
                "file":"mtn/flickHead_00.mtn",
                "sound":"snd/flickHead_00.mp3"
            },
            {
                "file":"mtn/flickHead_01.mtn",
                "sound":"snd/flickHead_01.mp3"
            },
            {
                "file":"mtn/flickHead_02.mtn",
                "sound":"snd/flickHead_02.mp3"
            }]
    }
}
